py2ls/.DS_Store
py2ls/.git/.DS_Store
py2ls/.git/COMMIT_EDITMSG
py2ls/.git/FETCH_HEAD
py2ls/.git/HEAD
py2ls/.git/config
py2ls/.git/description
py2ls/.git/hooks/applypatch-msg.sample
py2ls/.git/hooks/commit-msg.sample
py2ls/.git/hooks/fsmonitor-watchman.sample
py2ls/.git/hooks/post-update.sample
py2ls/.git/hooks/pre-applypatch.sample
py2ls/.git/hooks/pre-commit.sample
py2ls/.git/hooks/pre-merge-commit.sample
py2ls/.git/hooks/pre-push.sample
py2ls/.git/hooks/pre-rebase.sample
py2ls/.git/hooks/pre-receive.sample
py2ls/.git/hooks/prepare-commit-msg.sample
py2ls/.git/hooks/push-to-checkout.sample
py2ls/.git/hooks/update.sample
py2ls/.git/index
py2ls/.git/info/exclude
py2ls/.git/logs/HEAD
py2ls/.git/logs/refs/heads/main
py2ls/.git/logs/refs/remotes/origin/HEAD
py2ls/.git/logs/refs/remotes/origin/main
py2ls/.git/objects/.DS_Store
py2ls/.git/objects/01/d5bd8065e6860c0bd23ff9fa57161806a099e1
py2ls/.git/objects/09/08da26de58c114225ad81f484b80bf5d351b34
py2ls/.git/objects/0b/409e1bc918277010f5679b402d1d1dda53e15c
py2ls/.git/objects/12/c2808a1b3a4d0892a4154dfba1e2ae3770fa73
py2ls/.git/objects/14/449a0e6ba4ea2f1a73acf63ef91c9c6193f9ed
py2ls/.git/objects/15/a8e468aacfcb440e090020f36d0b985d45da23
py2ls/.git/objects/1a/b4585881a6a42889f01aa0cfe25fd5acfaf46f
py2ls/.git/objects/1c/3f92adda34344bcbbbf9d409c79855ae2aaea8
py2ls/.git/objects/1c/9314c5f69b9390068a2a8616875d974849d71f
py2ls/.git/objects/1d/fe9d9633b24ea560354f4f93d39c6e5f163ea0
py2ls/.git/objects/20/72c28e83f4347959d29f7b3a6c1fc3e4ee6b59
py2ls/.git/objects/24/6b368b986f758630c46dc02b7fa512b53422f7
py2ls/.git/objects/25/b796accd261b9135fd32a2c00785f68edf6c46
py2ls/.git/objects/27/aa6074f652bc6f7078f8647489d9ee8e24f0e2
py2ls/.git/objects/28/c2969d785c1b892c2a96b3f00eba63a59811b3
py2ls/.git/objects/2a/ae95d517d213b660bf4f65a4e0cfae7bb893eb
py2ls/.git/objects/2a/fdf45791a26d42ccead35ace76a8f0b2a56561
py2ls/.git/objects/30/a2f8da47ee947811dc8d993f5a06a45de374f4
py2ls/.git/objects/32/fd627b62fad7cf3b2f9e34ab9777126a0987ad
py2ls-0.2.7.15.dist-info/METADATA
py2ls-0.2.7.15.dist-info/WHEEL
py2ls-0.2.7.15.dist-info/RECORD
