Metadata-Version: 2.1
Name: py2ls
Version: 0.2.7.15
Summary: py(thon)2(too)ls
Author: Jianfeng
Author-email: Jianfeng.Liu0413@gmail.com
Requires-Python: >=3.5,<4.0
Classifier: Programming Language :: Python :: 3
Classifier: Programming Language :: Python :: 3.5
Classifier: Programming Language :: Python :: 3.6
Classifier: Programming Language :: Python :: 3.7
Classifier: Programming Language :: Python :: 3.8
Classifier: Programming Language :: Python :: 3.9
Classifier: Programming Language :: Python :: 3.10
Classifier: Programming Language :: Python :: 3.11
Classifier: Programming Language :: Python :: 3.12
Provides-Extra: full
Provides-Extra: ml
Provides-Extra: neuroscience
Provides-Extra: slim
Provides-Extra: superslim
Requires-Dist: GEOparse (>=2.0.4) ; extra == "full"
Requires-Dist: Pillow (>=11.2.1) ; extra == "full" or extra == "superslim" or extra == "slim"
Requires-Dist: PyYAML (>=6.0.1) ; extra == "full" or extra == "superslim" or extra == "slim"
Requires-Dist: SQLAlchemy (>=2.0.37) ; extra == "full"
Requires-Dist: adjustText (>=1.3.0) ; extra == "full" or extra == "superslim" or extra == "slim"
Requires-Dist: autogluon (>=1.2) ; extra == "full" or extra == "ml"
Requires-Dist: beautifulsoup4 (>=4.12.3) ; extra == "full" or extra == "slim"
Requires-Dist: catboost (>=1.2.8) ; extra == "full" or extra == "ml"
Requires-Dist: category_encoders (>=2.8.1) ; extra == "full"
Requires-Dist: chardet (>=3.0.4) ; extra == "full" or extra == "superslim" or extra == "slim"
Requires-Dist: cryptography (>=45.0.3) ; extra == "full" or extra == "superslim" or extra == "slim"
Requires-Dist: cycler (>=0.12.1) ; extra == "full" or extra == "superslim" or extra == "slim"
Requires-Dist: docx2pdf (>=0.1.8) ; extra == "full" or extra == "superslim" or extra == "slim"
Requires-Dist: fake-useragent (>=1.5.1) ; extra == "full" or extra == "slim"
Requires-Dist: folium (>=0.19.6) ; extra == "full"
Requires-Dist: fpdf (>=1.7.2) ; extra == "full" or extra == "superslim" or extra == "slim"
Requires-Dist: fuzzywuzzy (>=0.18.0) ; extra == "full" or extra == "superslim" or extra == "slim"
Requires-Dist: geopy (>=2.4.1) ; extra == "full"
Requires-Dist: gseapy (>=1.1.8) ; extra == "full"
Requires-Dist: gtts (>=2.5.4) ; extra == "full"
Requires-Dist: hdbscan (>=0.8.40) ; extra == "full"
Requires-Dist: imagecodecs (>=2025.3.30) ; extra == "ml"
Requires-Dist: img2pdf (>=0.5.1) ; extra == "full"
Requires-Dist: ipykernel (>=6.29.4) ; extra == "full" or extra == "superslim" or extra == "slim"
Requires-Dist: ipython (>=8.26.0) ; extra == "full" or extra == "slim"
Requires-Dist: langdetect (>=1.0.9) ; extra == "full"
Requires-Dist: lightgbm (>=4.6.0) ; extra == "full" or extra == "ml"
Requires-Dist: lxml (>=5.3.0) ; extra == "full" or extra == "superslim" or extra == "slim"
Requires-Dist: matplotlib (>=3.9.1) ; extra == "full" or extra == "superslim" or extra == "slim"
Requires-Dist: matplotlib-venn (>=1.1.2) ; extra == "full"
Requires-Dist: mne (>=1.6.1) ; extra == "neuroscience"
Requires-Dist: msoffcrypto-tool (>=5.4.2) ; extra == "full" or extra == "superslim" or extra == "slim"
Requires-Dist: neo (>=0.13.1) ; extra == "neuroscience"
Requires-Dist: networkx (>=3.3) ; extra == "full" or extra == "superslim" or extra == "slim"
Requires-Dist: nltk (>=3.8.1) ; extra == "full" or extra == "slim"
Requires-Dist: numerizer (>=0.2.3) ; extra == "full" or extra == "superslim" or extra == "slim"
Requires-Dist: numpy (>=1.26.4,<2.0.0) ; extra == "full" or extra == "superslim" or extra == "slim"
Requires-Dist: opencv-python-headless (>=4.10.0.84) ; extra == "full"
Requires-Dist: openlocationcode (>=1.0.1) ; extra == "full"
Requires-Dist: openpyxl (>=3.1.5) ; extra == "full" or extra == "superslim" or extra == "slim"
Requires-Dist: paddleocr (>=2.9.1,<3.0.0) ; extra == "full" or extra == "slim"
Requires-Dist: pandas (>=2.2.2) ; extra == "full" or extra == "superslim" or extra == "slim"
Requires-Dist: paramiko (>=3.4.1) ; extra == "full" or extra == "superslim" or extra == "slim"
Requires-Dist: pdf2image (>=1.17.0) ; extra == "full"
Requires-Dist: phonenumbers (>=8.13.51) ; extra == "full"
Requires-Dist: pingouin (>=0.5.4) ; extra == "full" or extra == "superslim" or extra == "slim"
Requires-Dist: pixels2svg (>=0.2.2) ; extra == "full"
Requires-Dist: premailer (>=3.10.0) ; extra == "full" or extra == "slim"
Requires-Dist: psutil (>=5.9.8) ; extra == "full" or extra == "superslim" or extra == "slim"
Requires-Dist: py-cpuinfo (>=9.0.0) ; extra == "superslim" or extra == "slim"
Requires-Dist: py7zr (>=0.22.0) ; extra == "full"
Requires-Dist: pyautogui (>=0.9.54) ; extra == "full"
Requires-Dist: pycryptodome (>=3.23.0) ; extra == "full"
Requires-Dist: pydeck (>=0.9.1) ; extra == "full"
Requires-Dist: pymupdf (>=1.26.1) ; extra == "full" or extra == "full" or extra == "superslim" or extra == "slim"
Requires-Dist: pypdf (>=5.6.1) ; extra == "full" or extra == "slim"
Requires-Dist: pyperclip (>=1.9.0) ; extra == "full"
Requires-Dist: pypinyin (>=0.54.0) ; extra == "full"
Requires-Dist: pytest (>=8.3.3) ; extra == "full" or extra == "superslim" or extra == "slim"
Requires-Dist: python-box (>=7.2.0) ; extra == "full" or extra == "slim"
Requires-Dist: python-dateutil (>=2.9.0.post0) ; extra == "full" or extra == "superslim" or extra == "slim"
Requires-Dist: python-docx (>=1.1.2) ; extra == "full" or extra == "superslim" or extra == "slim"
Requires-Dist: pytz (>=2024.1) ; extra == "full" or extra == "superslim" or extra == "slim"
Requires-Dist: pyvis (>=0.3.2) ; extra == "full"
Requires-Dist: qrcode (>=8.2) ; extra == "full" or extra == "superslim" or extra == "slim"
Requires-Dist: rarfile (>=4.2) ; extra == "full"
Requires-Dist: realesrgan (>=0.3.0) ; extra == "full"
Requires-Dist: regex (>=2024.5.15) ; extra == "full" or extra == "superslim" or extra == "slim"
Requires-Dist: rembg (>=2.0.57) ; extra == "full"
Requires-Dist: reportlab (>=4.4.2) ; extra == "full" or extra == "slim"
Requires-Dist: requests (>=2.32.3) ; extra == "full" or extra == "slim"
Requires-Dist: schedule (>=1.2.2) ; extra == "full"
Requires-Dist: scikit-image (>=0.23.2) ; extra == "full"
Requires-Dist: scikit-learn (>=1.5.1) ; extra == "full" or extra == "ml"
Requires-Dist: scipy (>=1.14.0) ; extra == "full" or extra == "superslim" or extra == "slim"
Requires-Dist: seaborn (>=0.13.2) ; extra == "full" or extra == "superslim" or extra == "slim"
Requires-Dist: selenium (>=4.23.1) ; extra == "full" or extra == "slim"
Requires-Dist: setuptools (>=72.1.0) ; extra == "full" or extra == "superslim" or extra == "slim"
Requires-Dist: skimpy (>=0.0.15) ; extra == "full"
Requires-Dist: skorch (>=1.0.0) ; extra == "full" or extra == "ml"
Requires-Dist: statsmodels (>=0.14.2) ; extra == "full"
Requires-Dist: streamlit (>=1.41.0) ; extra == "full"
Requires-Dist: streamlit-folium (>=0.25.0) ; extra == "full"
Requires-Dist: striprtf (>=0.0.29) ; extra == "full"
Requires-Dist: symspellpy (>=6.9.0) ; extra == "full"
Requires-Dist: tensorflow (>=2.19.0) ; extra == "full" or extra == "ml"
Requires-Dist: textblob (>=0.18.0.post0) ; extra == "full" or extra == "superslim" or extra == "slim"
Requires-Dist: tifffile (>=2024.12.12) ; extra == "ml"
Requires-Dist: torch (>=2.4.0) ; extra == "full" or extra == "ml"
Requires-Dist: tqdm (>=4.66.4) ; extra == "full" or extra == "slim"
Requires-Dist: umap (>=0.1.1) ; extra == "full"
Requires-Dist: validators (>=0.35.0) ; extra == "full"
Requires-Dist: venn (>=0.1.3) ; extra == "full"
Requires-Dist: webdriver-manager (>=4.0.1) ; extra == "full" or extra == "slim"
Requires-Dist: xgboost (>=3.0.2) ; extra == "full" or extra == "ml"
